LICENSE
MANIFEST.in
README.md
setup.py
docums_print_site_plugin/__init__.py
docums_print_site_plugin/exclude.py
docums_print_site_plugin/plugin.py
docums_print_site_plugin/renderer.py
docums_print_site_plugin/urls.py
docums_print_site_plugin/utils.py
docums_print_site_plugin.egg-info/PKG-INFO
docums_print_site_plugin.egg-info/SOURCES.txt
docums_print_site_plugin.egg-info/dependency_links.txt
docums_print_site_plugin.egg-info/entry_points.txt
docums_print_site_plugin.egg-info/requires.txt
docums_print_site_plugin.egg-info/top_level.txt
docums_print_site_plugin/css/print-site-docums.css
docums_print_site_plugin/css/print-site-enum-headings1.css
docums_print_site_plugin/css/print-site-enum-headings2.css
docums_print_site_plugin/css/print-site-enum-headings3.css
docums_print_site_plugin/css/print-site-enum-headings4.css
docums_print_site_plugin/css/print-site-enum-headings5.css
docums_print_site_plugin/css/print-site-enum-headings6.css
docums_print_site_plugin/css/print-site-material.css
docums_print_site_plugin/css/print-site.css
docums_print_site_plugin/js/print-site.js
docums_print_site_plugin/templates/cover_page.tpl
docums_print_site_plugin/templates/print_site_banner.tpl