Metadata-Version: 2.1
Name: docums-print-site-plugin
Version: 2.3
Summary: Docums plugin that combines all pages into one, allowing for easy export to PDF and standalone HTML.
Home-page: https://github.com/khanhduy1407/docums-print-site-plugin
Author: NKDuy
Author-email: kn145660@gmail.com
License: MIT
Keywords: docums plugin print pdf
Platform: UNKNOWN
Classifier: Operating System :: OS Independent
Classifier: Intended Audience :: Developers
Classifier: Programming Language :: Python
Classifier: Programming Language :: Python :: 3
Classifier: Programming Language :: Python :: 3.7
Classifier: Programming Language :: Python :: 3.8
Classifier: Programming Language :: Python :: 3.9
Classifier: Programming Language :: Python :: 3.10
Classifier: License :: OSI Approved :: MIT License
Classifier: Topic :: Documentation
Classifier: Topic :: Text Processing
Requires-Python: >=3.6
License-File: LICENSE
